MANIFEST.in
setup.py
src/greenlet.h
src/lru.hpp
src/uthash.h
src/infi/__init__.py
src/infi.tracing.egg-info/PKG-INFO
src/infi.tracing.egg-info/SOURCES.txt
src/infi.tracing.egg-info/dependency_links.txt
src/infi.tracing.egg-info/entry_points.txt
src/infi.tracing.egg-info/namespace_packages.txt
src/infi.tracing.egg-info/not-zip-safe
src/infi.tracing.egg-info/requires.txt
src/infi.tracing.egg-info/top_level.txt
src/infi/tracing/__init__.py
src/infi/tracing/__version__.py
src/infi/tracing/ctracing.pyx
src/infi/tracing/ctracing_log.pyx
src/infi/tracing/ctracing_log_serialize.pyx
src/infi/tracing/ctracing_trace_dump.pyx
src/infi/tracing/ctracing_trace_dump_unix.pyx
src/infi/tracing/defs.pxd
src/infi/tracing/thread_storage.cpp
src/infi/tracing/thread_storage.h
src/infi/tracing/thread_storage.pxd
src/infi/tracing/trace_dump.cpp
src/infi/tracing/trace_dump.h
src/infi/tracing/trace_dump.pxd
src/infi/tracing/trace_dump_unix.pxd
src/infi/tracing/trace_level_func_cache.pyx
src/infi/tracing/trace_message.h
src/infi/tracing/trace_message.pxd
src/infi/tracing/trace_message_ring_buffer.h
src/infi/tracing/trace_message_ring_buffer.pxd
src/infi/tracing/wait_and_ensure_exit.cpp
src/infi/tracing/wait_and_ensure_exit.h
src/infi/tracing/wait_and_ensure_exit.pxd
src/mintomic/core.h
src/mintomic/mintomic.h
src/mintomic/mintomic_gcc.c
src/mintomic/platform_detect.h
src/mintomic/private/core_gcc.h
src/mintomic/private/core_msvc.h
src/mintomic/private/mintomic_gcc_arm.h
src/mintomic/private/mintomic_gcc_x86-64.h
src/mintomic/private/mintomic_msvc.h
src/mintomic/private/stdint.h
src/mintsystem/datetime.h
src/mintsystem/mutex.h
src/mintsystem/semaphore.h
src/mintsystem/thread.h
src/mintsystem/tid.h
src/mintsystem/timer.h
src/mintsystem/gcc/datetime.c
src/mintsystem/gcc/mutex.c
src/mintsystem/gcc/semaphore.c
src/mintsystem/gcc/timer.c
src/mintsystem/private/mutex_gcc.h
src/mintsystem/private/mutex_msvc.h
src/mintsystem/private/semaphore_gcc.h
src/mintsystem/private/semaphore_msvc.h
src/mintsystem/private/thread_gcc.h
src/mintsystem/private/thread_msvc.h
src/mintsystem/private/tid_gcc.h
src/mintsystem/private/tid_msvc.h
src/mintsystem/private/timer_gcc.h
src/mintsystem/private/timer_msvc.h